inte_ae/__init__.py
inte_ae/action_items.py
inte_ae/admin_site.py
inte_ae/apps.py
inte_ae/baker_recipes.py
inte_ae/choices.py
inte_ae/list_data.py
inte_ae/urls.py
inte_ae/admin/__init__.py
inte_ae/admin/ae_followup_admin.py
inte_ae/admin/ae_initial_admin.py
inte_ae/admin/ae_susar_admin.py
inte_ae/admin/ae_tmg_admin.py
inte_ae/admin/death_report_admin.py
inte_ae/admin/death_report_tmg_admin.py
inte_ae/admin/death_report_tmg_second_admin.py
inte_ae/forms/__init__.py
inte_ae/forms/ae_followup_form.py
inte_ae/forms/ae_initial_form.py
inte_ae/forms/ae_susar_form.py
inte_ae/forms/ae_tmg_form.py
inte_ae/forms/death_report_form.py
inte_ae/forms/death_report_tmg_form.py
inte_ae/forms/death_report_tmg_second_form.py
inte_ae/migrations/0001_initial.py
inte_ae/migrations/0002_auto_20201124_1942.py
inte_ae/migrations/0003_auto_20201124_1943.py
inte_ae/migrations/0004_auto_20201124_2101.py
inte_ae/migrations/0005_auto_20210120_0005.py
inte_ae/migrations/0006_auto_20210203_2009.py
inte_ae/migrations/0007_auto_20210425_1637.py
inte_ae/migrations/__init__.py
inte_ae/models/__init__.py
inte_ae/models/ae_followup.py
inte_ae/models/ae_initial.py
inte_ae/models/ae_susar.py
inte_ae/models/ae_tmg.py
inte_ae/models/death_report.py
inte_ae/models/death_report_tmg.py
inte_ae/models/death_report_tmg_second.py
inte_ae/models/managers.py
inte_ae/pdf_reports/__init__.py
inte_ae/pdf_reports/ae_report.py
inte_ae/pdf_reports/death_report.py
inte_ae/pdf_reports/inte_pdf_report_mixin.py
inte_ae/templates/inte_ae/bootstrap3/ae_initial_description.html
inte_ae/templatetags/__init__.py
inte_ae/templatetags/inte_ae_extras.py
inte_auth/__init__.py
inte_auth/apps.py
inte_auth/codenames_by_group.py
inte_auth/urls.py
inte_auth/codenames/__init__.py
inte_auth/codenames/auditor.py
inte_auth/codenames/clinic.py
inte_auth/codenames/screening.py
inte_auth/codenames/unblinding.py
inte_consent/__init__.py
inte_consent/action_items.py
inte_consent/admin_site.py
inte_consent/apps.py
inte_consent/baker_recipes.py
inte_edc-0.1.74.dist-info/AUTHORS
inte_edc-0.1.74.dist-info/LICENSE
inte_edc-0.1.74.dist-info/METADATA
inte_edc-0.1.74.dist-info/WHEEL
inte_edc-0.1.74.dist-info/top_level.txt
inte_edc-0.1.74.dist-info/RECORD
