Metadata-Version: 2.1
Name: inte-edc
Version: 0.1.74
Summary: "INTE-AFRICA Trial EDC (https://www.isrctn.com/ISRCTN43896688)"
Home-page: https://github.com/clinicedc/inte-edc
Author: Erik van Widenfelt
Author-email: ew2789@gmail.com
License: GPL license, see LICENSE
Keywords: django edc EFFECT EDC,respond africa,clinicedc,clinical trials
Classifier: Environment :: Web Environment
Classifier: Framework :: Django
Classifier: Framework :: Django :: 3.2
Classifier: Intended Audience :: Developers
Classifier: Intended Audience :: Science/Research
Classifier: Operating System :: OS Independent
Classifier: Programming Language :: Python :: 3.8
Classifier: Programming Language :: Python :: 3.9
Classifier: License :: OSI Approved :: GNU General Public License v3 (GPLv3)
Requires-Python: >=3.9
License-File: LICENSE
License-File: AUTHORS
Requires-Dist: edc (==0.3.27)
Requires-Dist: respond-africa (==0.1.12)
Requires-Dist: beautifulsoup4
Requires-Dist: canned-views (==0.1.2)
